graphannis/__init__.py
graphannis/_ffi.py
graphannis/common.py
graphannis/cs.py
graphannis/errors.py
graphannis/graph.py
graphannis/test_cs.py
graphannis/util.py
graphannis/darwin-x86-64/libgraphannis.dylib
graphannis/linux-x86-64/libgraphannis.so
graphannis/win32-x86-64/graphannis.dll
graphannis-3.1.1.dist-info/LICENSE
graphannis-3.1.1.dist-info/METADATA
graphannis-3.1.1.dist-info/WHEEL
graphannis-3.1.1.dist-info/top_level.txt
graphannis-3.1.1.dist-info/RECORD
