Metadata-Version: 2.1
Name: graphannis
Version: 3.1.1
Summary: graphANNIS Python API
Home-page: https://github.com/korpling/graphANNIS-python/
Author: Thomas Krause
Author-email: thomaskrause@posteo.de
License: UNKNOWN
Platform: UNKNOWN
Classifier: Programming Language :: Python :: 3.6
Classifier: License :: OSI Approved :: Apache Software License
Classifier: Operating System :: POSIX :: Linux
Classifier: Operating System :: MacOS :: MacOS X
Classifier: Operating System :: Microsoft :: Windows
Requires-Dist: cffi >=1.0.0
Requires-Dist: networkx
